Metadata-Version: 2.1
Name: serializator-scocs
Version: 1.5
Summary: library for python serialization
Home-page: UNKNOWN
Author: Tarasenko Fyodor
Author-email: tarasenkafiodar@gmail.com
License: UNKNOWN
Platform: UNKNOWN
Classifier: Intended Audience :: Developers
Classifier: Programming Language :: Python
Classifier: Programming Language :: Python :: 3.9
Classifier: Operating System :: OS Independent
